podcast_llm/__init__.py
podcast_llm/config/__init__.py
podcast_llm/config/config.py
podcast_llm/config/config.yaml
podcast_llm/config/logging_config.py
podcast_llm/extractors/__init__.py
podcast_llm/extractors/audio.py
podcast_llm/extractors/base.py
podcast_llm/extractors/pdf.py
podcast_llm/extractors/plaintext.py
podcast_llm/extractors/utils.py
podcast_llm/extractors/web.py
podcast_llm/extractors/word.py
podcast_llm/extractors/youtube.py
podcast_llm/generate.py
podcast_llm/gui.py
podcast_llm/models.py
podcast_llm/outline.py
podcast_llm/research.py
podcast_llm/text_to_speech.py
podcast_llm/utils/__init__.py
podcast_llm/utils/checkpointer.py
podcast_llm/utils/embeddings.py
podcast_llm/utils/llm.py
podcast_llm/utils/rate_limits.py
podcast_llm/utils/text.py
podcast_llm/writer.py
podcast_llm-0.2.2.dist-info/LICENSE
podcast_llm-0.2.2.dist-info/METADATA
podcast_llm-0.2.2.dist-info/WHEEL
podcast_llm-0.2.2.dist-info/entry_points.txt
podcast_llm-0.2.2.dist-info/RECORD
