Metadata-Version: 2.1
Name: podcast-llm
Version: 0.2.2
Summary: An intelligent system that automatically generates engaging podcast conversations using LLMs and text-to-speech technology.
Home-page: https://github.com/evandempsey/podcast-llm
License: Creative Commons Attribution-NonCommercial 4.0 International (CC BY-NC 4.0)
Keywords: podcast,llm,ai
Author: Evan Dempsey
Author-email: evandempsey@gmail.com
Requires-Python: >=3.12,<4.0
Classifier: Development Status :: 3 - Alpha
Classifier: Intended Audience :: Developers
Classifier: License :: OSI Approved :: MIT License
Classifier: License :: Other/Proprietary License
Classifier: Programming Language :: Python :: 3
Classifier: Programming Language :: Python :: 3.12
Classifier: Programming Language :: Python :: 3.13
Requires-Dist: audioop-lts (>=0.2.0,<0.3.0) ; python_version >= "3.13" and python_version < "4.0"
Requires-Dist: elevenlabs (>=1.12.1,<2.0.0)
Requires-Dist: google-cloud-texttospeech (>=2.21.1,<3.0.0)
Requires-Dist: gradio (>=5.6.0,<6.0.0)
Requires-Dist: gradio-log (>=0.0.7,<0.0.8)
Requires-Dist: langchain (>=0.3.7,<0.4.0)
Requires-Dist: langchain-anthropic (>=0.3.0,<0.4.0)
Requires-Dist: langchain-community (>=0.3.7,<0.4.0)
Requires-Dist: langchain-google-genai (>=2.0.4,<3.0.0)
Requires-Dist: langchain-openai (>=0.2.8,<0.3.0)
Requires-Dist: lxml-html-clean (>=0.4.1,<0.5.0)
Requires-Dist: newspaper3k (>=0.2.8,<0.3.0)
Requires-Dist: openai (>=1.54.4,<2.0.0)
Requires-Dist: pydub (>=0.25.1,<0.26.0)
Requires-Dist: pypdf (>=5.1.0,<6.0.0)
Requires-Dist: python-docx (>=1.1.2,<2.0.0)
Requires-Dist: python-dotenv (>=1.0.1,<2.0.0)
Requires-Dist: tavily-python (>=0.5.0,<0.6.0)
Requires-Dist: wikipedia (>=1.4.0,<2.0.0)
Requires-Dist: youtube-transcript-api (>=0.6.2,<0.7.0)
Project-URL: Documentation, https://evandempsey.github.io/podcast-llm/
Project-URL: Repository, https://github.com/evandempsey/podcast-llm
